{
  "award_id": "asla奖_美国景观师协会奖_2026",
  "name": "ASLA奖（美国景观师协会奖）",
  "url": "https://www.asla.org/awards-events-main-landing/honors-awards",
  "scraped_at": "2026-04-24T08:45:38.719Z",
  "home_text": "Skip to content\nASLA logo. Green lines representing rolling fields.\nContact\nASLA Fund\nShop\nJoin\nLog in\nOpen search\nHonors & Awards\n\nASLA Honors and Awards recognize excellence across projects, people, and lifelong service—celebrating achievement, leadership, and lasting contributions to communities and the built and natural environments.\n\nThree Paths of Recognition\n\nCouncil of Fellows\n\nFellowship recognizes individuals' contributions to their profession and society at large through their work, leadership and management, knowledge, and service. The designation of Fellow is conferred on individuals in recognition of exceptional accomplishments over a sustained period of time.\n\nASLA Honors\n\nASLA Honors are reserved for the profession’s most exceptional contributors—those whose leadership, creativity, and service have changed lives and landscapes. Chosen by the ASLA Board of Trustees, these distinctions reflect the profound gratitude of the landscape architecture community.\n\nProfessional & Student Awards\n\nThe ASLA Awards honor the most accomplished designs and work of today professionals as well as spotlight the ideas and effort of the students who will shape tomorrow. Each year, leading practitioners, emerging designers, and students submit projects that restore habitats, strengthen communities, and elevate the human experience of place.",
  "char_count": 1356
}