{
  "award_id": "one_show奖_2026",
  "name": "One Show奖",
  "base_url": "https://oneshow.org/",
  "scraped_at": "2026-04-24T09:09:59.524Z",
  "pages": {
    "首页": {
      "url": "https://oneshow.org/",
      "text": "This website stores cookies on your computer to improve your website experience and provide more personalized services to you.\n\nAcceptDecline\nCEREMONY\nABOUT\nJURY\nINFO\nHELP\nENTRY SHOWCASE\nFINALISTS ANNOUNCED\n\nThe 2026 One Show Finalists are here!\nAwards will be publicly released May 14. Celebrate this year's winners with us May 15 in New York City at the ceremony.\n\nSee the List\nYOUR WORK, CRYSTALLIZED.\n\nThe One Show is where the world's best ideas rise to the top. For over 50 years, the Pencil has stood as one of the most respected honors in advertising, design, and beyond. And at the pinnacle: the Crystal Pencil, awarded only to Best of Discipline winners—peer-to-peer recognition from a jury of over 300 global creative leaders.\n\nWinning here is hard. That's why it matters. The One Show represents integrity, bold thinking, and the highest level of creative excellence across the industry.\n\nWith disciplines spanning the full spectrum of creativity—from timeless formats like Print and Film to cutting-edge categories in Gaming, Creative Use of AI, and the brand-new Creator Content discipline—The One Show continues to evolve alongside the work it honors. 2026 also sees the debut of The One Show Indies, a dedicated competition for independent shops proving you don't need scale to make impact.\n\nWinners are celebrated on May 15, 2026, during Creative Week in New York City—a week-long global festival from The One Club for Creativity, the world’s foremost nonprofit supporting and celebrating the creative community.\n\nThis is your moment. Explore the categories. Enter your boldest work. Claim your place among the world’s best.\n\n\nExplore Categories About The One Show 2026 Jury\nENTRY RESOURCES\nEntry Guide\nDeadlines & Dates\nEligibility & Rules\nDisciplines & Categories\nEntry Fees\nSubmission Media Specs\nOne Show FAQ\nContact Us\nNOTABLE FOR THE ONE SHOW 2026\nCategory Highlights\n\nExplore the latest categories shaping the future of advertising and design.\n\nCreative Use of AI\nCreator Content\nCreative Marketer\nDesign & Branding\nDesign in Advertising\nThe One Show Indies\n\nCommitment to Integrity\n\nIntegrity has always been the foundation of The One Show. For over 50 years, we have upheld the principle that true creative excellence must also be authentic, fair, and transparent. In 2026, we renew that commitment with even stronger standards that protect the legacy of the Pencil and the trust of the global creative community.\n\nRead more\n\nAward Intelligence\n\nFor the first time, entrants to The One Show can gain meaningful insight into how their work performed in the jury room—through a new AI-powered feedback tool designed to educate, clarify, and elevate future submissions.\n\nThis optional service transforms the often-mysterious judging process into actionable learning, helping entrants better understand why a piece resonated with judges and how award decisions were made.\n\nLearn more\n\nOne Show Pencils\n\nGOLD / SILVER / BRONZE PENCILS\nIcons of achievement that honor ideas distinguished by brilliance, craft, and lasting impact\n\nCRYSTAL PENCIL\nAwarded to Best of Disciplines, Best of Non-Profit, and the year's top ranked winners—including agencies, production studios, networks, and more\n\nBEST OF SHOW PENCIL\nThe pinnacle honor—recognizing the single most defining idea of the year\n\nExplore the Special Awards\nView\n\nCREATIVE MARKETER\nHonoring a senior brand leader whose vision and bravery elevate creativity as a core driver of success\n\nGREEN PENCIL\nCelebrating creativity that helps our planet thrive\n\nSDG PENCIL\nHonoring ideas that drive global progress\n\nFUSION PENCIL\nRecognizing creativity rooted in equity and inclusion\n\nPENTA PENCIL\nAwarding enduring excellence in brand-agency partnership\n\n\n\n   \n\nTHE ONE CLUB FOR CREATIVITY\n450 W 31ST STREET, 6TH FLOOR\nNEW YORK, NY 10001\n212.979.1900\n\nFOLLOW US\n     \nABOUT\nAbout\nBoard\nPartners\nPress\nContact\n\nAWARDS\nThe One Show\nADC Awards\nTDC Awards\nADCE Awards\nONE Asia\nYoung Ones\n\nMEMBERSHIP\nBecome a Member\nCorporate Members\nIndividual Members\nChapters\n\nPROGRAMS\nEducation\nInclusion & Diversity\nCreative Development\nGender Equality\n\n\n© 2026 The One Club for Creativity. All rights reserved."
    },
    "关于": {
      "url": "https://oneshow.org/about/",
      "text": "This website stores cookies on your computer to improve your website experience and provide more personalized services to you.\n\nAcceptDecline\nTHE ONE SHOW\n\nFinal Deadline: February 20, 2026\n\nABOUT THE ONE SHOW\n\nFor over five decades, The One Show has set the global benchmark for creative excellence. Recognized as the world's most prestigious award in advertising, design, and beyond, the coveted Gold Pencil has become a career-defining symbol of achievement — and the Crystal Pencil continues that legacy by honoring the very best of the best: the year's most groundbreaking work across every discipline.\n\nThe One Show is more than an awards program — it's where the global creative community comes together to celebrate bold ideas, powerful storytelling, and innovation that moves culture forward. Each year, thousands of agencies, brands, nonprofits, and independent creators from around the world enter, with their work judged by a jury of 300+ industry leaders representing every corner of the globe.\n\nProduced by The One Club for Creativity, the world's foremost nonprofit supporting and elevating the creative community, The One Show also serves a deeper purpose: as The One Club's most significant revenue generator, it powers the organization's year-round initiatives that make creative careers more accessible, inclusive, and sustainable. From mentorship programs to DEI initiatives, from student education to professional development, proceeds from The One Show go directly back into supporting creatives at every stage of their career journey.\n\nWinning here isn't just recognition — it's a place in creative history, and a contribution to the future of the industry.\n\nTHE ONE SHOW GALA\n\nMark your calendar: on Friday, May 15, 2026, The One Show returns to New York City. This is the industry's most anticipated event of the year — a not-to-be-missed gathering of the world's leading creatives, agencies, brands, and innovators, all coming together to honor the ideas that define culture.\n\nThe evening is the grand finale of Creative Week, a weeklong celebration of creativity that fills New York with award shows, panels, workshops, portfolio reviews, and networking. But the Gala is the pinnacle: a night dedicated to celebrating the ideas and people shaping the future of creativity.\n\nThe Gala stands as the creative industry's most essential night — uniting the people, ideas, and work that define our field.\n\nAT A GLANCE\nQuick Facts\nFounded: 1973\nEntries: 18,000 in 2025\nCountries Represented: 62 in 2025\nAwards Presented: 658 Pencils in 2025\nEntry Deadlines\n\nSuper Early Deadline: October 31, 2025\nEarly Deadline: December 12, 2025\nRegular Deadline: January 23, 2026\nExtended Deadline: February 6, 2026\nFinal Deadline: February 20, 2026\n\n2025 Insights Report\n\nDive into what today's top creatives are celebrating—and why. The 2025 Insights Report spotlights six major themes uncovered by 300+ global judges, complete with discipline deep-dives, trends, and actionable takeaways.\nView the 2025 Insights Report\n\nIN THE PRESS\n\nVisit The One Club for Creativity's press page for more.\n\nAd Age, May 16 2025\nSpotify's 'Spreadbeats' continues its awards run, topping... One Show\n\nHorizont, May 15 2025\nServiceplan is the big winner at the One Show Awards\n\nCampaign India, May 16 2025\nPencils with a point: India's creative edge sharpens\n\nBizcommunity, May 16 2025\nOne Show winners: Joe Public, Promise and TBWA\\Hunt Lascaris\n\nCALL FOR ENTRY\n\nThis year's “Your Victory, Crystalized” branding for The One Show 2026 features animations from a comprehensive visual and motion system created by the independent creative house NotReal, based in Madrid and Buenos Aires, part of a larger campaign to be used at award shows during Creative Week. Adaptations for the 2026 campaign animations were art-directed and designed into final assets by Design Army, based in Washington, DC.\n\nCopy developed by Reed Words, based in New York and London, plays off the award name to describe different aspects of this highest creative achievement.\n\nWHAT YOUR ENTRY FEES SUPPORT\n\nThe One Club for Creativity, the world's foremost nonprofit organization whose mission is to support and celebrate the global creative community, uses the revenue generated from entry fees to fund a number of initiatives for our industry. Learn more about The One Club and all our programs and events.\n\nMembers of The One Club for Creativity become part of an international community that stands behind our mission to champion excellence in advertising and design in all its forms. We offer memberships on individual and corporate levels. Learn more about becoming a member.\n\nLEARN MORE ABOUT ONE CLUB PROGRAMS:\nWhere Are All The Black People - Diversity Conference\nPortfolio Night\nSaturday Career Workshops\nCreative Boot Camps\nCreative Leaders Retreat\nNext Creative Leaders\nONE School\nONE Creator Lab\n\n\n   \n\nTHE ONE CLUB FOR CREATIVITY\n450 W 31ST STREET, 6TH FLOOR\nNEW YORK, NY 10001\n212.979.1900\n\nFOLLOW US\n     \nABOUT\nAbout\nBoard\nPartners\nPress\nContact\n\nAWARDS\nThe One Show\nADC Awards\nTDC Awards\nADCE Awards\nONE Asia\nYoung Ones\n\nMEMBERSHIP\nBecome a Member\nCorporate Members\nIndividual Members\nChapters\n\nPROGRAMS\nEducation\nInclusion & Diversity\nCreative Development\nGender Equality\n\n\n© 2026 The One Club for Creativity. All rights reserved."
    },
    "评审": {
      "url": "https://oneshow.org/jury/",
      "text": "This website stores cookies on your computer to improve your website experience and provide more personalized services to you.\n\nAcceptDecline\nTHE ONE SHOW 2026 JURY\nJUMP TO JURY:\n\nBrand-Side / In-House\nBranded Entertainment\nCreative Effectiveness\nCreative Use of AI\nCreative Use of Data\nCreative Use of Technology\nCreator Content\nCultural Driver\nDesign & Branding\nDesign in Advertising\nDirect Marketing\nExperiential & Immersive\nFilm & Video\nGaming\nHealth & Wellness\nIntegrated / Omnichannel\nInteractive, Online & Mobile\nIP & Product Design\nMoving Image Craft\nMusic & Sound Craft\nOut of Home\nPharma\nPrint & Promotional\nPublic Relations\nRadio & Audio-First\nSocial Media\nThe Indies\nFusion Pencil\nGreen Pencil\nSDG Pencil\nCreative Marketer\nPenta Pencil\n\n\nJury Presidents\n\n\n\nBRAND-SIDE / IN-HOUSE JURY\nHelen Pak Jury President\nBrand-Side / In-House\n\nSenior Vice President, Creative - Marketing / Design / Content\nThe Walt Disney Company\nAnaheim / Celebration / Glendale\n\n\nSeán Doyle\n\nGroup Creative Director\nPinterest\nLondon\n\n\nCandice Drakeford\n\nCreative Director\nWNBA\nBrooklyn\n\n\nTaylor Erin\n\nExecutive Creative Director\nInstacart\nLaguna Beach\n\n\nMatei Goncea\n\nEurope Marketing Director - Creative Strategy\nCoca-Cola\nBucharest\n\n\nDanielle Hawley\n\nGlobal Head of Creative & Brand\nUber\nLafayette\n\n\nSuhayl Limbada\n\nMarket Lead & Chief Marketing Officer\nKFC Thailand\nBangkok\n\n\nTom Pettus\n\nExecutive Creative Director\nAmazon\nSanta Monica\n\n\nSharmin Rahman\n\nHead of Corporate Brand\nGrameenphone Ltd.\nDhaka\n\n\nLex Remalante\n\nAssociate Creative Director\nThe LEGO Group\nBillund\n\n\nBRANDED ENTERTAINMENT JURY\nRajdeepak Das Jury President\nBranded Entertainment\n\nChairman - Leo, South Asia & Chief Creative Officer - Publicis Groupe, South Asia\nLeo\nMumbai\n\n\nParker Adame\n\nGroup Creative Director\nMedia Arts Lab\nLos Angeles\n\n\nJenna Anderson\n\nChief Creative Officer\nFish Agency\nToronto\n\n\nJeannette Bohné\n\nMD Creative\nBohné\nBerlin\n\n\nDaniel \"DC\" Cherry III\n\nGlobal Chief Marketing Officer\nVans\nCosta Mesa\n\n\nGabriel Jardim\n\nExecutive Creative Director\nVML\nNew York\n\n\nMatt Murphy\n\nGlobal Chief Creative Officer\n72andSunny\nLos Angeles\n\n\nAlberto Orte\n\nExecutive Creative Director\nThe Martin Agency\nNew York\n\n\nNayaab Rais\n\nExecutive Creative Director\nFP7 McCann\nDubai\n\n\nHelen Rhodes\n\nCCO\nGrey London\nLondon\n\n\nRoss Taylor\n\nGroup Executive Creative Director\nHavas Play Network\nLondon\n\n\nJuan Woodbury\n\nCCO / Global Head of Branded Content & Entertainment\nBento Entertainment / Wolf\nChicago\n\n\nRichard Yu\n\nCo-Founder & Chief Creative Officer\nROCK YU Creative\nTaipei\n\n\nCREATIVE EFFECTIVENESS JURY\nJane Lin-Baden Jury President\nCreative Effectiveness\n\nCEO APAC, Member of the Global Management Committee\nPublicis Groupe\nShanghai\n\n\nJen Costello\n\nGlobal CSO\nTBWA\nNew York\n\n\nJuan Pablo Garcia\n\nManaging Director\nDAVID\nBogota\n\n\nPierre Loo\n\nExecutive Creative Director\nOmnicom Health Asia Pacific\nHong Kong\n\n\nDennis Lück\n\nChief Creative Officer\nbrinkertlück creatives\nZurich\n\n\nJulian Morgan\n\nHead of Strategy\nRethink\nToronto\n\n\nBrent Nelsen\n\nGlobal Chief Innovation & Strategy Officer\nEdelman\nVancouver\n\n\nDani Richa\n\nChairman and CEO\nImpact BBDO\nDubai\n\n\nMaureen Rutabingwa\n\nGlobal Head of Spirits Innovation, Africa\nDiageo\nLondon\n\n\nChristine Shoaf\n\nChief Global Client Officer\nMomentum Worldwide\nNew York\n\n\nAnna Vogt\n\nEMEA CSO\nVML\nStockholm\n\n\nCREATIVE USE OF AI JURY\nDan Gardner Jury President\nCreative Use of AI\n\nCo-founder, Executive Chairman\nCode and Theory\nNew York\n\n\nSalma Aboukar\n\nAI Design Partner\nSilverside\nLondon\n\n\nHenry Cowling\n\nChief Innovation Officer\nMonks\nSan Anselmo\n\n\nMel (Melissa) Daniels\n\nRegional Head of Innovation\nTBWA\nSingapore\n\n\nFaye Garland\n\nCreative Technology Manager\nIPG/Omnicom\nManchester\n\n\nDominik Heinrich\n\nGlobal Head of Design Intelligence and AI Experiences\nThe Coca-Cola Company\nAtlanta\n\n\nThomas Knüwer\n\nChief Creative Officer\nAccenture Song\nHamburg\n\n\nNadine Müller\n\nCreative Director\nOmnicom Health Germany\nFrankfurt am Main\n\n\nIsabel Perry\n\nGlobal EVP of Strategy\nDEPT®\nLondon\n\n\nLeilanni Todd\n\nCreative Director\nIndependent\nBrooklyn\n\n\nRogier Vijverberg\n\nChief Creative Hero\nSUPERHEROES\nBrooklyn\n\n\nCREATIVE USE OF DATA + CREATIVE USE OF TECHNOLOGY JURY\nBeth Keamy Jury President\nCreative Use of Data + Creative Use of Technology\n\nChief Digital Officer\nTBWA\\Media Arts Lab\nLos Angeles\n\n\nTina Allan\n\nGlobal Chief Solutions Architect\nMcCann Global\nNew York\n\n\nYasushi Arikawa\n\nChief Creative Officer\nVML & Ogilvy Japan\nTokyo\n\n\nGene Brutty\n\nCo-Founder, Executive Creative Director\nImagine If Labs\nPerth\n\n\nNoel Bunting\n\nChief Creative Officer\nPublicis London\nLondon\n\n\nPaulo Damasceno\n\nGroup Creative Director\nVIRTUE Worldwide\nNew York\n\n\nAmaresh Godbole\n\nCEO, Digital Technology Business\nPublicis Groupe India\nMumbai\n\n\nMihae Mukaida\n\nSVP, Executive Director of Innovation\nMcCann\nNew York\n\n\nOswaldo Sa\n\nECD\nVML\nNew York\n\n\nRohit Thawani\n\nHead of Social and Activations\nSpecial US\nLos Angeles\n\n\nCULTURAL DRIVER JURY\nNadja Lossgott Jury President\nCultural Driver\n\nJoint Chief Creative Officer\nAMV BBDO\nLondon\n\n\nOmid Amidi\n\nCCO\nMcKinney\nNew York\n\n\nAbi Aquino\n\nChief Creative Officer\nTREYNA\nMakati City\n\n\nMitchell Collinson\n\nExecutive Creative Director\nDentsu Mozambique\nMaputo\n\n\nHoward Finkelstein\n\nGroup Creative Director\nMischief\nBrooklyn\n\n\nRoberta Harada\n\nECD\nVML\nSão Paulo\n\n\nCaio Maroni Giannella\n\nCreative Director\nApple\nCupertino\n\n\nOmar Polo\n\nChief Creative Officer\nMcCann Panamá\nPanamá City\n\n\nRamiro Raposo\n\nSVP, ECD\nThe Community\nMiami\n\n\nLila Talitha\n\nGroup Executive Creative Director\nFuture Creative Network\nJakarta\n\n\nShelby Tamura\n\nCreative Director\nMother\nLos Angeles\n\n\nGuillermo Vega\n\nChief Creative Officer\nOgilvy NA\nNew York\n\n\nDESIGN & BRANDING JURY\nDebbie Millman Jury President\nDesign & Branding\n\nDesigner, Author, Educator, Podcast Host\nSchool of Visual Arts\nNew York\n\n\nClayton Caetano\n\nHead of Brand & Design\nItaú Unibanco S.A.\nSão Paulo\n\n\nJean-Jacques Charrais\n\nCreative Director\nW Conrad Design\nBoulogne-Billancourt\n\n\nChee Wee Choo\n\nCo-Founder/ECD\nMUMA Malaysia\nKuala Lumpur\n\n\nTeman Evans\n\nGlobal Chief of Design\nGeneral Mills\nGolden Valley\n\n\nSebastian Huynh\n\nDesign, Brand, Content and Experience strategist\nIBM\nBrooklyn\n\n\nValeria Moreiro\n\nCo-Founder & Executive Creative Director\nNotReal\nMadrid\n\n\nEmily Oberman\n\nPartner\nPentagram\nNew York\n\n\nAneri Patel\n\nAssociate Design Director\nNo.one (AndUs Group)\nDubai\n\n\nAlberto Rigau\n\nPrincipal\nEstudio Interlínea\nSan Juan\n\n\nDESIGN IN ADVERTISING JURY\nNils Leonard Jury President\nDesign in Advertising\n\nCreative Founder\nUncommon Creative Studio\nLondon\n\n\nGuto Andrade\n\nVP Creative\nVerizon\nNew York\n\n\nRita Coetzer\n\nExecutive Creative Director\nPublicis Groupe\nJohannesburg\n\n\nGabriela Freire\n\nCreative Director\nPAPER\nGuayaquil\n\n\nHernan Ibanez\n\nHead of Art & Design\nOgilvy\nNew York\n\n\nPrerna Mehra\n\nExecutive Creative Director\nMullenlowe MENA\nDubai\n\n\nMurilo Melo\n\nGlobal Head Of Design\nGUT Design\nSão Paulo\n\n\nBen Miles\n\nChief Design Officer\nR/GA\nSydney\n\n\nLuiz Sanches\n\nGlobal Chief Creative & Design Officer\nKimberly-Clark\nNew York\n\n\nErica Thwaites\n\nVP, Creative Director\nFCB Health New York\nNew York\n\n\nUna Wei\n\nChief Art Officer\nLxU\nBeijing\n\n\nDIRECT MARKETING JURY\nAndré Toledo Jury President\nDirect Marketing\n\nChief Creative Officer\nDAVID\nNew York\n\n\nOlivier Aumard\n\nExecutive Creative Director\nBETC\nParis\n\n\nSami Basut\n\nCCO\nTBWA\\Istanbul\nIstanbul\n\n\nYael Cesarkas\n\nSVP Executive Strategy Director\nR/GA\nNew York City\n\n\nCatalin Dobre\n\nCCO & CO-CEO\nMcCann\nBucharest\n\n\nHadeel Hmaidi\n\nIntegrated Marketing Lead\nTikTok\nDubai\n\n\nJohn Koay\n\nChief Creative Officer\nOmnicom Advertising\nHong Kong\n\n\nJean Morrow\n\nGroup Creative Director\nCoinbase\nSan Francisco\n\n\nChristian Sánchez\n\nCCO\nVML\nLima\n\n\nAndrea Sarcullo\n\nSenior Vice President Group Creative Director\nLeo\nChicago & New York\n\n\nTim Welsh\n\nHead of Corporate Communications and Reputation\nTBWA Canada\nToronto\n\n\nEXPERIENTIAL & IMMERSIVE + INTEGRATED / OMNICHANNEL JURY\nErh Ray Jury President\nIntegrated + Experiential & Immersive\n\nCEO & CCO\nBETC HAVAS Brazil\nSão Paulo\n\n\nNoor Akar\n\nGroup Creative Director\nTBWA\\RAAD\nDubai\n\n\nMariana Cárdenas\n\nPremium Brands & High-End Business Director\nAb InBev | Bavaria Colombia\nBogota\n\n\nJason Carmel\n\nGlobal Lead, Creative Data\nVML\n\n\nDustin Duke\n\nGlobal Executive Creative Director\nAmazon, Brand Innovation Lab\nNew York\n\n\nJenna Fizel\n\nManaging Director, Emerging Technology Lab\nIDEO\nCambridge\n\n\nMatthäus Frost\n\nECD\nServiceplan Neo\nMunich\n\n\nAntonin Jacquot\n\nACD\nMarcel\nParis\n\n\nSnooze Kambuwa\n\nExecutive Creative Director\nOgilvy South Africa\nJohannesburg\n\n\nJung A Kim\n\nCEO/CCO\nInnocean\nSeoul\n\n\nNoor Samra\n\nNational Planning Director\nFCB Interface\nMumbai\n\n\nFILM & VIDEO JURY\nJason Xenopoulos Jury President\nFilm & Video\n\nChief Creative Officer VML USA & Global CCO, WPP Ford\nVML\nNew York\n\n\nClaudia Alves\n\nCo-Founder\nFLUXA Filmes\nRio De Janeiro\n\n\nAlex Ames\n\nSr. Director of Content & Creative Excellence\nThe Coca-Cola Company\nAtlanta\n\n\nAli Brown\n\nPresident\nPRETTYBIRD\nCulver City\n\n\nXolisa Dyeshana\n\nChief Creative Officer\nJoe Public\nSouth Africa\n\n\nPaul Gregson\n\nCreative Director\nBear Meets Eagle On Fire\nSydney\n\n\nPeter Khoury\n\nRegional CCO\nTBWA\\Asia\nSingapore\n\n\nSophia Lindholm\n\nSenior Art Director / Group Creative Director\nForsman & Bodenfors\nGothenburg\n\n\nOlga Mykhalets\n\nChief Creative Officer\nPostmen\nKyiv\n\n\nAnuwat Nitipanont\n\nChief Creative Officer\nYDM Thailand\nBangkok\n\n\nWesley Phelan\n\nExecutive Creative Director\nOgilvy\nNew York\n\n\nJose Ramirez\n\nCreative Director\nGUT\nMiami\n\n\nJulie Scelzo\n\nCCO, Dentsu Creative US\nDentsu Creative\nNew York\n\n\nLaurent Simon\n\nChief Creative Officer\nBMB\nLondon\n\n\nNeda Zag\n\nEditor\nCold Cutz\nDubai\n\n\nGAMING JURY\nThanh Dao Jury President\nGaming\n\nCEO\nJung von Matt NERD GmbH\nHamburg\n\n\nKatrina Alvarez-Jarratt\n\nExecutive Creative Director\nPublicis Groupe\nSydney\n\n\nSue Anderson\n\nVP, Creative\nRoblox\nSan Mateo\n\n\nMax Bass\n\nVP, Emerging Connections\nGALE\nLos Angeles\n\n\nChesang' Koech\n\nAssociate Creative Director\nOgilvy Africa\nNairobi\n\n\nBrent Koning\n\nEVP, Global Head of Gaming\ndentsu\nLondon\n\n\nMichelle Perez Barruos\n\nFounder & CEO, MPB Licensing – General Manager, Feenix Studio\nMPB Licensing & Feenix Studio\nMadrid\n\n\nIzzy Serruya\n\nCreative Director\nLePub\nSão Paulo\n\n\nMike Sutherland\n\nChief Creative Officer\nadam&eveDDB\nLondon\n\n\nJens Waernes\n\nChief Creative Officer\nVML Copenhagen\nCopenhagen\n\n\nHEALTH & WELLNESS + PHARMA JURY\nTim Hawkey Jury President\nHealth & Wellness + Pharma\n\nChief Creative Officer\nAREA 23, an IPG Health Company\nNew York\n\n\nTash Beecher\n\nGlobal & EMEA Creative Director\nSyneos Health Communications\n\n\nJoao Camacho\n\nCCO India & Middle East\nHavas Life\nDubai\n\n\nPancho Gonzalez\n\nCo-Founder & Chief Creative Officer\nInbrax Chile\nSantiago\n\n\nSarah Ko\n\nExecutive Creative Director\nPublicis Groupe\nSingapore\n\n\nLulu Lu\n\nChief Creative Officer\nVML\nTaipei\n\n\nJohn McPartland\n\nExecutive Creative Director EMEA\nOgilvy Health UK\nLondon\n\n\nThomas Mori\n\nGroup Creative Director & Head of Art\nFCB\nNew York\n\n\nCamila Rodrigues\n\nCreative Director\n72andSunny\nAmsterdam\n\n\nJay Schacher\n\nEVP, Executive Design Director\nKlick Health\nToronto\n\n\nMegan Skelly\n\nCCO\nHavas Lynx\nNew York\n\n\nINTERACTIVE ONLINE & MOBILE JURY\nTseliso Rangaka Jury President\nInteractive, Online & Mobile\n\nChief Creative Officer\nAccenture Song\nJohannesburg\n\n\nAlex Adati\n\nExecutive Creative Director\nArtplan\nSão Paulo\n\n\nCamilla Clerke\n\nGlobal Executive Creative Director: Unilever\nOgilvy\nLondon\n\n\nRita Harbie\n\nSenior Creative Director\nSaatchi & Saatchi\nDubai\n\n\nJuuso Helander\n\nHead of Innovation\nNitro\nHelsinki\n\n\nMinah Kim\n\nUX Director\nCheil Worldwide Inc\nSeoul\n\n\nRahul Mathew\n\nChief Creative Officer & Executive Director\nDDB MUDRA GROUP\nMumbai\n\n\nFernanda Navilli\n\nCreative Director\nVTPro Design\nLos Angeles\n\n\nBongiwe Neema Nouse\n\nCreative Director\nThe Odd Number\nJohannesburg\n\n\nImran Sheikh\n\nGroup Executive Creative Director, US Craft Lead\nR/GA\nNew York\n\n\nJim Sowden\n\nGlobal Innovation Creative Director\nSundogs\nNew York\n\n\nIP & PRODUCT DESIGN JURY\nYasu Sasaki Jury President\nIP & Product Design\n\nGlobal Chief Creative Officer\ndentsu\nTokyo\n\n\nSebastian Bullorini\n\nChief Creative Officer\nDe la Cruz - Ogilvy Puerto Rico\nSan Juan\n\n\nDavid DeCheser\n\nGlobal Chief Creative Officer\nValtech\nNew York\n\n\nAshish Deshpande\n\nCo-Founder, Director Product Experience\nElephant Design\nPune\n\n\nAngus Dick\n\nCreative Director\nMap Project Office\nLondon\n\n\nMaggie Michella\n\nAssociate Creative Director\nOgilvy\nSingapore\n\n\nAlessandra Muccillo\n\nGroup Creative Director\nMonks\nSão Paulo\n\n\nOved Valadez\n\nFounder\nINDUSTRY\nPortland\n\n\nKyoko Yonezawa\n\nHead of Innovation\nTBWA\\HAKUHODO\nTokyo\n\n\nMOVING IMAGE CRAFT & PRODUCTION JURY\nJoaquín Cubría Jury President\nMoving Image Craft & Production\n\nChief Creative Officer & Partner\nGUT\nBuenos Aires\n\n\nPierre Cazenave-Kaufman\n\nExecutive Producer, Founder\nSoldats\nParis\n\n\nSerra Chehade\n\nHead of Production\n‿ and us\nDubai\n\n\nCamila De Biaggi\n\nExecutive Producer/Partner\nBanquet VFX\nNew York\n\n\nFrancesca Ferracini\n\nGroup Creative Director\nOgilvy\nNew York\n\n\nFlorencia Gastelu\n\nInternational Executive Producer\nLANDIA\nBuenos Aires\n\n\nCharlotte Glennon\n\nGeneral Manager\nColenso BBDO\nAuckland\n\n\nDiane McArter\n\nFounder & President\nFurlined\nLos Angeles\n\n\nLubabalo Mtati\n\nExecutive Creative Director\nM&C Saatchi & Abel\nJohannesburg\n\n\nSam Schwier\n\nCG Lead\nHeckler\nSingapore\n\n\nVarun Shah\n\nManaging Partner\nPublicis Production\nMumbai\n\n\nNaoko Tajima\n\nDirector\nWonderworld\nTokyo\n\n\nStephen Tisdalle\n\nChief Marketing Officer\nFuture Standard\nPhiladelphia\n\n\nMonica Tyson\n\nExecutive Producer\nFramestore\nNew York\n\n\nRodrigo Vargas\n\nHead of Production Global Accounts & Creative Excellence\nMcCann\nMadrid\n\n\nMUSIC & SOUND CRAFT JURY\nCece Wyldeck Jury President\nMusic & Sound Craft\n\nEMEA Director of Creative Development\nMassiveMusic\nAmsterdam\n\n\nKhalil Bachooali\n\nFounder & Executive Producer\nOffroad Films\nMumbai\n\n\nAisha Blackwell\n\nHead of Production Services\nServiceplan MAKE\nMunich\n\n\nWill Bone\n\nMusic Director\nPingado Áudio\nSão Paulo\n\n\nJane Cronk\n\nExecutive Creative Director\nBBH\nNew York\n\n\nYash Deb\n\nCo-Founder and Creative Partner\nThe Bar Africa\nNairobi\n\n\nPerry Fair\n\nCCO\nIndependent\n\n\nBruce Ikeda\n\nCreative Director / Music Director / Producer\nJKD Collective Inc.\nTokyo\n\n\nKelly McCluskey\n\nExec Producer/Partner\nGrayson Music\nToronto\n\n\nRebecca O'Neill\n\nHead of Production\nJohannes Leonardo\nNew York\n\n\nRani Zarina Vaz\n\nManaging Parter\nSUPREME MUSIC\nNew York\n\n\nMichael Zarcone\n\nHead of Content Feature Production\nApple Music & Podcasts\nLos Angeles\n\n\nOUT OF HOME + PRINT & PROMOTIONAL JURY\nJessica Apellaniz Jury President\nOut of Home + Print & Promotional\n\nCCO\nWieden+Kennedy\nMexico\n\n\nThiago Carvalho\n\nGroup Creative Director\nTranslation\nNew York\n\n\nSofia Cursach\n\nExecutive Creative Director\nVML\nBuenos Aires\n\n\nGlen D'Souza\n\nIndependent Creative\nCanada\n\n\nEamonn Dixon\n\nExecutive Creative Director\nGoodby, Silverstein & Partners\n\n\nAngie Featherstone\n\nCreative Director\nThe Secret Little Agency\nSingapore\n\n\nEstefanio Holtz\n\nExecutive Creative Director\nSpecial US\nNew York\n\n\nKatie Jensen\n\nExecutive Creative Director\nTBWA\\Chiat\\Day\\NY\nNew York\n\n\nRicardo John\n\nPartner/cco\nIsla\nSão Paulo\n\n\nRana Khoury\n\nCo-Founder/Creative "
    },
    "时间": {
      "url": "https://oneshow.org/dates/",
      "text": "This website stores cookies on your computer to improve your website experience and provide more personalized services to you.\n\nAcceptDecline\nIMPORTANT DATES\n\nJUMP TO:\n\nEntry Deadlines\nJudging\nFinalists / Awards\nENTRY DEADLINES\n\nThe One Show 2026 will be accepting entries in five submission periods. Please note that entry fees increase during each deadline period, based on when an entry is completed in the system, regardless of entry creation date. Please refer to the disciplines or fees pages for more information.\n\nOnce an entry is completed and closed, it is confirmed for the show and the entrant becomes responsible for payment without exception.\n\nAll payments must reach The One Club within 15 days of the invoice date.\n\nSuper Early Deadline: October 31, 2025\nEarly Deadline: December 12, 2025\nRegular Deadline: January 23, 2026\nExtended Deadline: February 6, 2026\nFinal Deadline: February 20, 2026\n\nIMPORTANT NOTE:\nThe One Show 2026 is accepting physical entry materials for select categories in the Design in Advertising and Design & Branding disciplines. All physical entry materials must be received at The One Club no later than February 20, 2026. Categories accepting physical materials can be viewed here for more details.\n\nJUDGING\nFirst Round:\nEntries submitted in all deadlines will be judged in January – March 2026.\nNOTE: Physical entries in the Design in Advertising and Design & Branding disciplines will be judged in-person in April 2026.\nNOTE: After Round 1 judging is complete, entrants will be notified if their work has advanced to Round 2.\nSecond Round:\nEntries that advance to Second Round will be judged in March 2026.\nNOTE: Physical entries in the Design for Advertising and Design & Branding disciplines will be judged in-person in April 2026.\nFinal Discussions:\nJuries will participate in Final Discussions to determine the Finalists (Pencil or Merit winners) in late March – April 2026.\nFINALISTS / AWARDS\n\nAll work that has won an award – Pencil or Merit – is considered a Finalist. The specific type of award and special awards will be publicly revealed during Creative Week, May 11-15, 2026.\n\nFinalists Notified: April 14, 2026\n\nFinalists Announced: April 16, 2026\nDate is subject to change.\nFinalist Confirmations:\nAll finalists must confirm that all information related to their winning entries is complete and accurate.\nEngraving and Shipping Information Due: April 17, 2026\nAll Other Finalist Confirmations Due: April 20, 2026\nThis includes Media, Information, Credits, Verification, and Ceremony Attendance\nThe One Show Awards Ceremony: May 15, 2026\nThe One Show celebratory gala will take place on May 15, 2026 in New York City.\nPencils\nTo make celebrating your win even easier, we ship awards directly to all winners. For those joining us in person, on-stage awards will be available at the show. However you receive your pencils, your moment of glory is on its way!\n\n\n   \n\nTHE ONE CLUB FOR CREATIVITY\n450 W 31ST STREET, 6TH FLOOR\nNEW YORK, NY 10001\n212.979.1900\n\nFOLLOW US\n     \nABOUT\nAbout\nBoard\nPartners\nPress\nContact\n\nAWARDS\nThe One Show\nADC Awards\nTDC Awards\nADCE Awards\nONE Asia\nYoung Ones\n\nMEMBERSHIP\nBecome a Member\nCorporate Members\nIndividual Members\nChapters\n\nPROGRAMS\nEducation\nInclusion & Diversity\nCreative Development\nGender Equality\n\n\n© 2026 The One Club for Creativity. All rights reserved."
    },
    "类别": {
      "url": "https://oneshow.org/categories",
      "text": "This website stores cookies on your computer to improve your website experience and provide more personalized services to you.\n\nAcceptDecline\nDISCIPLINES & CATEGORIES\n\nThe One Show categories vary by Discipline. Use the links below to view the different Discipline categories, entry fees, and submission media options.\n\nNOTE: The exact same piece may only be entered into a maximum of three (3) different categories per discipline (excluding craft and innovation categories).\n\nView Categories By Type View Special Awards View Entry Fees View Submission Media Specs\n\nBRAND-SIDE / IN-HOUSE\nBrand-Side / In-House recognizes work produced by a brand's internal creative team that focuses on the advertising and marketing of their product or service.\nNOTE: External partners including agencies and production companies may have been part of the campaign execution, but the creative idea must have originated from the brand.\nVIEW CATEGORIES\nBRANDED ENTERTAINMENT\nBranded Entertainment celebrates work where the audience experience comes first and the brand plays a supporting, yet integral role. It goes beyond traditional product placement or sponsorship, delivering films, series, music, games, or other content designed to engage on its own merits while naturally weaving in the brand. The emphasis is on storytelling, craft, and audience enjoyment—where advertising and cultural content converge.\nNOTE: Traditional commercial spots do not generally qualify for this discipline and should instead be entered in the Film & Video discipline.\nVIEW CATEGORIES\nCREATIVE EFFECTIVENESS\nCreative Effectiveness recognizes bold creative work that produced measurable impact in meeting defined business objectives and played a key role in achieving a brand's purpose.\nNOTE: Work entered in this discipline must be published or aired between January 1, 2024 – February 20, 2026.\nNOTE: Work can only be entered into one Creative Effectiveness category.\nVIEW CATEGORIES\nCREATIVE USE OF AI\nCreative Use of AI (Artificial Intelligence) recognizes the groundbreaking use and integration of AI in work for brands, agencies and individuals. It celebrates the partnership between human creativity and artificial intelligence in the evolution of creative work and process.\nNOTE: No special equipment will be used for judging. The required submission media must showcase the technology.\nVIEW CATEGORIES\nCREATIVE USE OF DATA\nCreative Use of Data recognizes work in which the gathering, interpretation, and/or display of data is integral in defining or communicating the brand's message.\nVIEW CATEGORIES\nCREATIVE USE OF TECHNOLOGY\nCreative Use of Technology recognizes work for which technology played an integral role in defining or communicating the brand's message.\nVIEW CATEGORIES\nCREATOR CONTENT\nWork conceived and executed in partnership with individual creators, where the creator’s voice, platform, or style is integral to the idea. This discipline celebrates content that leverages creators’ unique influence and authenticity to connect brands with audiences in ways that traditional advertising alone cannot achieve.\nVIEW CATEGORIES\nCULTURAL DRIVER\nCultural Driver recognizes influential ideas and executions that had a sizable impact in their respective cultures and environments, created new trends, or transformed culture. In addition to the quality of the idea and execution, work in this discipline will be judged through the lens of the specific culture it impacted.\nVIEW CATEGORIES\nDESIGN & BRANDING\nDesign & Branding celebrates premium design across brand and product communications. This discipline recognizes excellence in identity, packaging, publications, environments, and other applications where design elevates how a brand is expressed and experienced.\nNOTE: Design work created specifically for an advertising campaign may be entered in the Design in Advertising discipline.\nVIEW CATEGORIES\nDESIGN IN ADVERTISING\nDesign in Advertising recognizes work where design is central to the concept and execution of an advertising campaign. This discipline celebrates how typography, identity, packaging, environments, and other design systems are applied to campaigns in ways that amplify the idea, engage audiences, and elevate the brand experience.\nVIEW CATEGORIES\nDIRECT MARKETING\nDirect Marketing recognizes communications to a clear target group, with a call to action, and defined results.\nVIEW CATEGORIES\nEXPERIENTIAL & IMMERSIVE\nExperiential & Immersive recognizes temporary or permanent brand experiences that use physical and/or digital environments to engage audiences and create a connection with the brand.\nVIEW CATEGORIES\nFILM & VIDEO\nFilm & Video recognizes advertising in the form of commercial spots that aired on television, in cinemas, or online.\nVIEW CATEGORIES\nGAMING\nGaming recognizes interactive experiences that use gameplay to entertain, inform, and create community. It includes work that is built around a brand that engages the user and adds to the gaming experience.\nNOTE: No special equipment will be used for judging. The required submission media must showcase the game.\nNOTE: Work can be brands utilizing existing games, or standalone games built for a brand.\nVIEW CATEGORIES\nHEALTH & WELLNESS\nHealth & Wellness recognizes work that promotes a brand, product, service, or message that assists in a person or animal's health and well-being.\nNOTE: Campaigns for regulated products should be entered into the Pharma discipline.\nVIEW CATEGORIES\nINTEGRATED / OMNICHANNEL\nIntegrated / Omnichannel recognizes creative concepts and messaging unified across multi-channel campaigns.\nNOTE: Campaigns must consist of 3-10 elements, executed in at least 3 mediums. \nVIEW CATEGORIES\nINTERACTIVE, ONLINE & MOBILE\nInteractive, Online & Mobile recognizes advertising communicated through digital channels including websites, mobile applications, and other digital media.\nVIEW CATEGORIES\nIP & PRODUCT DESIGN\nIP & Product Design recognizes original products, experiences, and intellectual properties created by a brand. This discipline includes physical or digital products, branded utilities, ownable figures, narrative assets, and other creations that extend a brand’s presence and create lasting connections with audiences.\nVIEW CATEGORIES\nMOVING IMAGE CRAFT & PRODUCTION\nMoving Image Craft & Production recognizes the specialized skills demonstrated in the creation and production of branded content videos and commercial spots.\nVIEW CATEGORIES\nMUSIC & SOUND CRAFT\nMusic & Sound Craft recognizes the specialized skills demonstrated in the production or execution of original, licensed, and adapted music as well as sound in videos, commercial spots, or other work utilizing audio as a key component of its creative.\nVIEW CATEGORIES\nOUT OF HOME\nOut of Home recognizes advertising in public spaces, delivered via physical or digital mediums.\nVIEW CATEGORIES\nPHARMA\nPharma recognizes communications created for products or services that diagnose, treat, prevent, or advocate for medical conditions.\nNOTE: Campaigns for non-regulated products should be entered into the Health & Wellness discipline.\nVIEW CATEGORIES\nPRINT & PROMOTIONAL\nPrint & Promotional recognizes advertising communicated through printed publications and other physical collateral.\nVIEW CATEGORIES\nPUBLIC RELATIONS\nPublic Relations recognizes campaigns, programs, and tactics that are led by strategic communication and earned influence, rather than traditional paid advertising. These initiatives actively engage audiences, spark cultural conversation, and build credibility in service of a clear objective.\nNOTE: This includes areas such as public affairs, community affairs, and related practices.\nVIEW CATEGORIES\nRADIO & AUDIO-FIRST\nRadio & Audio recognizes advertising in the form of audio-based content such as broadcast or online commercial spots and podcasts.\nVIEW CATEGORIES\nSOCIAL MEDIA\nSocial Media recognizes work where social platforms are central to the idea, strategy, and execution. While the work may exist as part of a broader campaign, the social components must be conceived as social-first and built around the behaviors, features, and culture of the platforms themselves.\nVIEW CATEGORIES\nTHE INDIES\nVIEW CATEGORIES\n\n\n   \n\nTHE ONE CLUB FOR CREATIVITY\n450 W 31ST STREET, 6TH FLOOR\nNEW YORK, NY 10001\n212.979.1900\n\nFOLLOW US\n     \nABOUT\nAbout\nBoard\nPartners\nPress\nContact\n\nAWARDS\nThe One Show\nADC Awards\nTDC Awards\nADCE Awards\nONE Asia\nYoung Ones\n\nMEMBERSHIP\nBecome a Member\nCorporate Members\nIndividual Members\nChapters\n\nPROGRAMS\nEducation\nInclusion & Diversity\nCreative Development\nGender Equality\n\n\n© 2026 The One Club for Creativity. All rights reserved."
    },
    "规则": {
      "url": "https://oneshow.org/eligibility/",
      "text": "This website stores cookies on your computer to improve your website experience and provide more personalized services to you.\n\nAcceptDecline\nELIGIBILITY & RULES\n\nReview the below eligibility dates, rules, and restrictions for The One Show to ensure that your work meets the requirements for entry.\n\nJUMP TO:\n\nEligibility Dates\nRules & Regulations\nSubmission Restrictions\nInternational Entries\nNon-Compliance\nTerms & Conditions\nELIGIBILITY DATES\n\nAll work must have been first published or aired between the dates listed below.\n\"Published\" means the advertisement or work appeared in a form of mass media viewed by a substantial audience.\n\nEntry Eligibility Dates:\nJanuary 1, 2025 – February 20, 2026\nCreative Effectiveness Eligibility:\nJanuary 1, 2024 – February 20, 2026\nGreen Pencil Eligibility:\nJanuary 1, 2024 – February 20, 2026\nSDG Pencil Eligibility:\nJanuary 1, 2022 – February 20, 2026\nPenta Pencil Eligibility:\nJanuary 1, 2016 – February 20, 2026\nNOTE: At least one campaign included in the submission must have launched between January 1, 2025 – February 20, 2026.\n\n\n\nNOTE: If you were unable to enter work into The One Show 2025, and your work does not fall into the 2026 eligibility dates, please contact oneshow@oneclub.org.\n\nRULES & REGULATIONS\nEntries must be submitted by industry professionals only, including freelancers. Student, spec work, or non-commissioned passion projects are not accepted.\nWork produced on behalf of The One Club for Creativity and its programming, including The One Show, ADC Annual Awards, Type Directors Club, Young Ones Student Awards, etc. is not eligible.\nThe One Club reserves the right to disqualify entries submitted without proper documentation verifying the creation of the work.\nALL ENTRY FEES ARE NON-REFUNDABLE AND NON-TRANSFERABLE.\nBy submitting entries into the competition, entrants are committing to pay for all entry fees in full.\nSUBMISSION RESTRICTIONS\nThe exact same work may only be entered into a maximum of 3 different categories per discipline (excluding craft and innovation categories).\nThe exact same work may NOT be entered multiple times into the same category, regardless of the deadline period.\nDifferent executions of the exact same work may NOT be entered into the same category.\nThe exact same work may be entered into The One Show two consecutive years ONLY IF:\n1\n\nThe work falls within the eligibility requirements for both seasons.\n\n2\n\nAt least one of the following is true:\n\nThe work did NOT win an award (Pencil, Merit, Special Award) in any category in the previous season.\nOR\nThe work is entered into Creative Effectiveness, Green Pencil, SDG Pencil, or Penta Pencil in the current season.\nOR\nThe work was only entered into the R&D category in the IP & Product Design discipline in a previous season.\n\nINTERNATIONAL ENTRIES\n\nThe One Show accepts and celebrates entries from around the world. All work should be submitted in its original language.\n\nEnglish translations are required for all work in another language:\n\nImage and Audio Media:\nFor entries in a language other than English, provide an English translation in the \"Judging Description / Translation\" field with the individual media.\nVideo Media:\nFor video entries in a language other than English, provide English subtitles in the video or a translation in the \"Judging Description / Translation\" field with the individual media.\nPDF Media:\nAll PDF entries must be submitted in English.\nURL Media:\nFor URL entries in a language other than English, use the \"Judging Description / Translation\" field with the individual media to provide any necessary instructions in English.\nPhysical Materials:\nFor all Physical entries in a language other than English, use the \"English Translation\" field in the Information section on the entry.\nNON-COMPLIANCE\n\nThe One Club for Creativity, Inc. (The One Club) reserves the right to review all entries questioned during the judging process. Not complying with the rules and/or attempting to enter fraudulent work will result in the following:\n\nAn agency, the regional office of an agency network, or an independent agency that enters work made for nonexistent clients, or made and run without a client's approval, will be banned from entering The One Show for 3 years.\nThe team credited on the fake work will be banned from entering The One Show for 3 years.\nAn agency, the regional office of an agency network, or an independent agency that enters an ad that has run once, on late night TV, or has only run because the agency produced a single ad and paid to run it themselves, will be banned from entering The One Show for 3 years.\nAny entrant found to have intentionally misrepresented outcomes, case study narratives, or data claims — including the use of falsified footage, fabricated executions, or deceptive editing — will be banned from entering The One Show for 3 years.\n\nNOTE: The One Club reserves the right to review \"late-night, ran-once\" and launch versions. If The One Club, at its sole discretion, determines that the work was created expressly for award show entry, the penalty will hold.\n\nTERMS & CONDITIONS\n\nThe One Club for Creativity will require proof of publication for all entries. The One Club has the right to request additional proof of initial publication and/or air date, to be submitted within 15 days of the request.\n\nAll entry fees are non-refundable and non-transferable. By submitting entries into the competition, the entrant is committing to pay for all entry fees in full.\n\nThe entrant grants permission to The One Club for Creativity to show, copy or play the entries at such times as The One Club deems appropriate. The One Club reserves the right to make available for educational and reference purposes, including electronic publishing, any material entered into The One Show. The entrant or person submitting the work is responsible for ensuring that any copyrighted material has been approved or released and does not hold The One Club legally responsible for any matters pertaining to the creation of the work. If any network or local television or radio station shall agree to telecast a news or other program relating to The One Show, the entrant further agrees to obtain any permissions and to absorb talent or other residual charges incurred by inclusion of his or her entry in the program, if required.\n\nAll entries are subject to the rules of The One Show as stated on the entry site. Decisions of judges on all matters during judging, including qualifications and categories, are final. Any disputes that may arise will be decided by The One Club Board of Directors. The One Club reserves the right to disqualify work that it finds to be fatally compromised as to originality or veracity after review and final decision by The One Club Board of Directors.\n\n\n\n   \n\nTHE ONE CLUB FOR CREATIVITY\n450 W 31ST STREET, 6TH FLOOR\nNEW YORK, NY 10001\n212.979.1900\n\nFOLLOW US\n     \nABOUT\nAbout\nBoard\nPartners\nPress\nContact\n\nAWARDS\nThe One Show\nADC Awards\nTDC Awards\nADCE Awards\nONE Asia\nYoung Ones\n\nMEMBERSHIP\nBecome a Member\nCorporate Members\nIndividual Members\nChapters\n\nPROGRAMS\nEducation\nInclusion & Diversity\nCreative Development\nGender Equality\n\n\n© 2026 The One Club for Creativity. All rights reserved."
    },
    "费用": {
      "url": "https://oneshow.org/fees/",
      "text": "This website stores cookies on your computer to improve your website experience and provide more personalized services to you.\n\nAcceptDecline\nENTRY FEES\n\nThere is no registration fee to create an account. However, there is a fee for each entry that you submit. These fees vary by category.\n\nListed below are the entry fees for each discipline and deadline period. All entry fees are in U.S. Dollars (USD).\n\nNOTE: \"Single or Series\" fees refer to categories in that discipline that accept both Single and Series entries. The fee is the same for all entries in these categories.\n\nView Disciplines & Categories View Payment Options\n\nNOTE:\nCredit card transactions are subject to a 3% processing fee.\nWire transfer transactions are subject to a $35 USD processing fee.\nIMPORTANT:\nAll entry fees are non-refundable and non-transferable.\nBy submitting entries into the competition, entrants are committing to pay for all entry fees in full.\n\nJUMP TO:\n\nEntry Fees by Discipline & Deadline\nCurrency Value Adjustment\nENTRY FEES BY DISCIPLINE & DEADLINE\nDISCIPLINES\tSUPER EARLY DEADLINE\nOctober 31, 2025\tEARLY DEADLINE\nDecember 12, 2025\tREGULAR DEADLINE\nJanuary 23, 2026\tEXTENDED DEADLINE\nFebruary 6, 2026\tFINAL DEADLINE\nFebruary 20, 2026\nCreative Use of Data\nCreative Use of Technology\nCultural Driver\nExperiential & Immersive\nGaming\nIP & Product Design\nMusic & Sound Craft\tSingle or Series: $550\tSingle or Series: $600\tSingle or Series: $625\tSingle or Series: $725\tSingle or Series: $900\nBranded Entertainment\nDesign in Advertising\nFilm & Video\nInteractive, Online & Mobile\nMoving Image Craft\nOut of Home\nPrint & Promotional\nRadio & Audio-First\nSocial Media\tSingle: $550\nSeries: $700\nSingle or Series: $550\tSingle: $600\nSeries: $750\nSingle or Series: $600\tSingle: $625\nSeries: $775\nSingle or Series: $625\tSingle: $725\nSeries: $875\nSingle or Series: $725\tSingle: $900\nSeries: $1050\nSingle or Series: $900\nCreator Content\nDesign & Branding\tSingle: $400\nSeries: $550\nSingle or Series: $400\tSingle: $450\nSeries: $600\nSingle or Series: $450\tSingle: $475\nSeries: $625\nSingle or Series: $475\tSingle: $575\nSeries: $725\nSingle or Series: $575\tSingle: $750\nSeries: $900\nSingle or Series: $750\nBrand-Side / In-House\nHealth & Wellness\nPharma\nPublic Relations\tSingle or Series: $550\nIntegrated: $750\tSingle or Series: $600\nIntegrated: $800\tSingle or Series: $625\nIntegrated: $825\tSingle or Series: $725\nIntegrated: $925\tSingle or Series: $900\nIntegrated: $1100\nCreative Use of AI\tSingle or Series: $550\nPioneer/Innovation: $400\tSingle or Series: $600\nPioneer/Innovation: $450\tSingle or Series: $625\nPioneer/Innovation: $475\tSingle or Series: $725\nPioneer/Innovation: $575\tSingle or Series: $900\nPioneer/Innovation: $750\nDirect Marketing\tSingle: $550\nSeries: $700\nSingle or Series: $550\nIntegrated: $750\tSingle: $600\nSeries: $750\nSingle or Series: $600\nIntegrated: $800\tSingle: $625\nSeries: $775\nSingle or Series: $625\nIntegrated: $825\tSingle: $725\nSeries: $875\nSingle or Series: $725\nIntegrated: $925\tSingle: $900\nSeries: $1050\nSingle or Series: $900\nIntegrated: $1100\nIntegrated / Omnichannel\tIntegrated: $750\tIntegrated: $800\tIntegrated: $825\tIntegrated: $925\tIntegrated: $1100\nCreative Effectiveness\nCreative Marketer\tSingle or Series: $750\tSingle or Series: $800\tSingle or Series: $825\tSingle or Series: $925\tSingle or Series: $1100\nFusion Pencil\tSingle or Series: $550\tSingle or Series: $600\tSingle or Series: $625\tSingle or Series: $725\tSingle or Series: $900\nGreen Pencil\nSDG Pencil\tSingle or Series: $400\tSingle or Series: $450\tSingle or Series: $475\tSingle or Series: $575\tSingle or Series: $750\nPenta Pencil\tSeries: $1000\tSeries: $1100\tSeries: $1200\tSeries: $1300\tSeries: $1500\nCURRENCY VALUE ADJUSTMENT\n\nAutomatic discounts will be applied to entries from specific countries / regions to account for an unfair disadvantage from the value of their local currency in comparison to the US Dollar.\n\nThis reduction of entry fees will be automatically applied during checkout.\nNOTE: Fee adjustment does not apply to processing fees.\n\n10% ADJUSTMENT\nArgentina\nBahrain\nBrazil\nChile\nEcuador\nGuatemala\nHonduras\nHungary\nPanama\nPeru\n15% ADJUSTMENT\nBangladesh\nBelarus\nBolivia\nBulgaria\nColombia\nDominican Republic\nEgypt\nEl Salvador\nGeorgia\nIndia\nIndonesia\nJordan\nKazakhstan\nKenya\nLebanon\nMalaysia\nMorocco\nMyanmar\nNicaragua\nPakistan\nPhilippines\nRomania\nSerbia\nSouth Africa\nThailand\nTunisia\nTurkey\nUkraine\nUzbekistan\nVietnam\n\n\n   \n\nTHE ONE CLUB FOR CREATIVITY\n450 W 31ST STREET, 6TH FLOOR\nNEW YORK, NY 10001\n212.979.1900\n\nFOLLOW US\n     \nABOUT\nAbout\nBoard\nPartners\nPress\nContact\n\nAWARDS\nThe One Show\nADC Awards\nTDC Awards\nADCE Awards\nONE Asia\nYoung Ones\n\nMEMBERSHIP\nBecome a Member\nCorporate Members\nIndividual Members\nChapters\n\nPROGRAMS\nEducation\nInclusion & Diversity\nCreative Development\nGender Equality\n\n\n© 2026 The One Club for Creativity. All rights reserved."
    },
    "FAQ": {
      "url": "https://oneshow.org/faq/",
      "text": "This website stores cookies on your computer to improve your website experience and provide more personalized services to you.\n\nAcceptDecline\nFREQUENTLY ASKED QUESTIONS\n\nIs your question not listed below? Please refer to the pages listed under the Info nav or contact us.\n\nJUMP TO:\n\nAccount\nEntering\nRequirements\nEntry Fees\nEligibility\nPayment\nEntry Showcase\nJudging\nFinalists / Winners\nOther\nACCOUNT\nDo I need to make a new account?\nNo, you will not need to make a new account if you have entered before. If you already have a One Club or One Show account, sign in with your email and password to create your entries.\nIf you are new to The One Show, you can easily create an account which will allow you to enter.\n\nDo I have to be a One Club member to enter?\nNo. You do not have to be a member of The One Club to enter. However, we always recommend the benefits of One Club membership! For more details on membership, click here.\n\nHow do students enter The One Show?\nThe One Show is for professionals only, but we encourage students to enter the Young Ones Student Awards. Click here for more details.\n\n\nENTERING\nHow do I enter?\nIf you already have a One Club or One Show account, sign in with your email and password to create your entries.\nIf you are new to The One Show, you can easily create an account which will allow you to enter.\n\nAre physical entries accepted?\nThe Design discipline is accepting physical entries this year in select categories. Entries into all other categories must be submitted digitally.\nSee more questions about submission requirements.\n\nWhat is the deadline for entries?\nThe One Show has different submission periods. To view the different deadlines, click here.\n\nWhat are the categories?\nThe One Show categories vary by Discipline. Click here to view all Disciplines.\n\nCan I edit or add credits after I have completed checkout and closed my entries?\nYes. Credits are not used for judging, and they can still be edited on closed entries.\nNOTE: A Primary credit is required for all entries. Judging is anonymous, so the jury will not see this.\n\nCan I edit my Entry Title or Client/Brand after I have completed checkout and closed my entries?\nNo. You will not be able to edit your Entry Title or Client/Brand on the entry details section for closed entries. If you need to make a change, please email oneshow@oneclub.org. Be sure to include the Entry ID number in your email.\n\n\nCan I supply or edit my judging media after I have completed checkout and closed my entries?\nNo. The entry system will not allow you to close your entries until you have added the required media.\nNOTE: Judging and Supporting media cannot be edited after an entry has been submitted. Requests sent to The One Show team cannot be guaranteed and may incur additional fees.\n\nCan I delete my entries after I have completed checkout and closed them?\nNo, you will not be able to delete your entries once you have completed checkout and closed them.\nNOTE: All entry fees are non-refundable and non-transferable. By submitting entries into the competition, entrants are committing to pay for all entry fees in full.\n\nCan I duplicate my entries or do I need to create each entry separately?\nOn an entry in your Open/Draft or Closed/Submitted list, click the CREATE COPY button to duplicate that entry into another category or categories.\nNOTE: You may be required to make adjustments to the new entry if it does not fit the new category's requirements.\n\n\nCan I duplicate my entries into the ADC Awards?\nYes! As a partner awards competition within The One Club for Creativity, you can create an entry in either The One Show or ADC Awards entry system and then create a duplicate copy in the other competition.\nEmail oneshow@oneclub.org with a list of the entries (by Entry ID) that you'd like to duplicate. Please note that it may take up to 48 hours to appear in your Open/Draft list in the second entry system.\nNOTE: After the entries appear in your account in the new entry system, you will need to:\nSelect the category for the new entry\nMake adjustments to information and/or media that does not fit the new category's requirements\nProceed to checkout in both competition systems\nNOTE: Once duplicated, each entry must be edited in each system separately.\nLearn more about cloning entries into ADC Awards.\n\nCan I wait until the deadline to start my entries?\nWe highly recommend starting your entries in advance of the final deadline. See more tips on making the Final Deadline less stressful here.\n\n\nWhat can I continue editing on my entry after I submit?\nReference the chart below to see which parts of an entry will be locked and when.\n\tENTRY CREATION\tPROCESSING\tWINNER PROCESS\n\tDraft / Open\nEntries\tSubmitted / Closed\nEntries\tPrepared for\nJudging\tFinalist Entry\nTo Confirm\tFinalist Entry\nConfirmed\nEntry Details\tunlocked\tlocked\tlocked\tlocked\tlocked\nMedia – Judging\tunlocked\tlocked\tlocked\tlocked\tlocked\nMedia – Supporting\tunlocked\tlocked\tlocked\tlocked\tlocked\nMedia – Reference Images\tunlocked\tunlocked\tlocked\tlocked\tlocked\nMedia – Archive\tn/a\tn/a\tn/a\tunlocked\tlocked\nInformation\tunlocked\tunlocked\tlocked\tunlocked\tlocked\nCredits\tunlocked\tunlocked\tunlocked\tunlocked\tlocked\nEntry Showcase Opt-In\tunlocked\tunlocked\tunlocked\tn/a\tn/a\n\n\n\nNOTE: Judging and Supporting media cannot be edited after an entry has been submitted. Requests sent to The One Show team cannot be guaranteed and may incur additional fees.\nNOTE: Entries are prepared for judging in the order they are received, typically within 1-2 business days. \nNOTE: The media displayed in the One Club Archive can be confirmed or replaced for Finalist (winning) entries after Finalists are notified.\nNOTE: After Finalists (winners) are notified, the Entry Showcase will no longer be public.\n\n\n\nSUBMISSION REQUIREMENTS\nCan I send in physical items for judging?\nThe Design discipline is accepting physical entries this year in select categories. Entries into all other categories must be submitted digitally.\n\n\nWill my physical materials be returned?\nPhysical items submitted cannot be returned due to the logistics of physical judging and shipping.\n\nWhere can I find labels for my physical entries?\nEntry labels can be generated and printed for both Open/Draft and Closed/Submitted entries for which you have selected to submit as a physical item.\nOpen/Draft individual entries:\nYou can find an individual entry label directly in the \"Media\" section on that entry.\nClosed/Submitted individual entries:\nYou can find individual entry label(s) on each entry on the Closed/Submitted Entries list in the Media Submitted column.\nA full set of labels from a single invoice:\nYou can find a full set of entry labels and a mailing label on your Invoices page.\nPlease note that the mailing label should be attached to the outside of your package in addition to any shipping labels necessary as provided by your shipping company.\nFor more information on submitting physical entries, click here.\n\nWhat media is accepted?\nEach category accepts different media. Click here to view the Discipline categories and their submission media requirements.\nClick here to view details on file specifications for different media types.\n\nWhat information is needed to create an entry?\nAll One Show entries require the following information on the project, regardless of category. Individual categories may have additional requirements.\nGeneral Project Information:\nEntry Title: Provide the name of the project, or the campaign name.\nNOTE: Do not put the category into the Entry Title.\nClient / Brand: Who is the client on the project and/or what brand is it promoting?\nSingle or Series: Choose from: Single (1), Series (2+). Required only for categories that allow both Single and Series entries. On these categories, the fee is the same for Single and Series entries.\nClient Type: Choose from: Consumer / Brand, Business to Business, Corporate Social Responsibility, Non-Profit\nVertical Market: The specific industry to which your promoted product or service relates. Click here to view the full list of available Vertical Markets.\nLaunch Date: The month and year in which the work first ran, aired, was published, etc.\nBackground: Describe the challenge presented, problem being addressed, cultural background, or other key components to the initial brief. (max 300 words)\nCreative Idea: A summary of the creative idea behind the work. (max 300 words)\nInsights & Strategy: The insights and strategy that informed the final work and its intended purpose. (max 300 words)\nExecution: Explain critical elements of the final execution of the work including craft, placement, tone, and other specific aspects of the creation and implementation of the work. (max 300 words)\nResults: The results or outcome of the work such as reach, response, engagement, sales, awareness, etc. (max 300 words)\nNOTE: Results are not required at the time of entry in most categories. This information can be added or updated on winning entries prior to release in the public Winners Archive.\n\nDo I need to provide an English translation for my entry?\nYes. English translations are required for all work in another language.\n\nImage and Audio Media: For entries in a language other than English, please provide an English translation in the \"Judging Description / Translation\" field with your individual media.\nVideo Media: For video entries in a language other than English, please provide English subtitles in the video or a translation in the \"Judging Description / Translation\" field with your individual media.\nPDF Media: All PDF entries must be submitted in English.\nURL Media: For URL entries in a language other than English, use the \"Judging Description / Translation\" field with your individual media to provide any necessary instructions in English.\nPhysical Materials: For all physical entries in a language other than English, use the \"English Translation\" field in the Information section on the entry.\nENTRY FEES\nHow much does it cost to enter?\nThere is a fee for each entry that you submit. These fees vary by category.\nTo view a summary of all fees, click here.\nTo view the different Discipline categories, click here.\nNOTE: All fees listed are in U.S. Dollars (USD).\n\nWhat is a \"Single or Series\" fee?\nSome categories allow both Single (1 piece) or Series (2+ pieces) to be entered into the same category. For these categories, the fee is the same for Single or Series entries.\n\nIs there a registration fee?\nThere is no registration fee to create an account.\n\nAre there additional fees if I win?\nThere are no additional fees for entries winning a One Show Pencil, Merit, or Special Award. If you would like to purchase additional Pencil trophies, please visit The One Club Store.\n\nWhere do my entry fees go?\nThe One Club for Creativity is a non-profit organization. All entry fees from The One Show go towards The One Club for Creativity's education, gender equality, diversity and inclusion, and professional development intiatives. Learn more.\n\n\nELIGIBILITY\nIs my entry eligible to be entered?\nClick here to see if your entry meets One Show guidelines.\n\nMy spot only ran once. Is it eligible?\nYes. Your spot is eligible.\n\nAre there any rules or regulations for submitting entries?\nYes. Click here to see the rules, regulations, and submission restrictions for entry.\nNOTE: Not complying with the rules and regulations will result in your entries being disqualified from the competition.\n\nHow does The One Club define a fake ad?\nThe One Club defines \"fake ads\" as: Ads created for nonexistent clients, ads made to run without a client's approval, and ads created expressly for award shows that are run once to meet the requirements of a tear sheet.\n\nWhat are the penalties of entering a fake ad?\nAn agency, the regional office of an agency network, or an independent agency that enters work made for nonexistent clients, or made and run without a client's approval, will be banned from entering The One Show for 3 years.\nThe team credited on the fake work will be banned from entering The One Show for 3 years.\nAn agency, the regional office of an agency network, or an independent agency that enters an ad that has run once, on late night TV, or has only run because the agency produced a single ad and paid to run it themselves, will be banned from entering The One Show for 3 years.\nAny entrant found to have intentionally misrepresented outcomes, case study narratives, or data claims — including the use of falsified footage, fabricated executions, or deceptive editing — will be banned from entering The One Show for 3 years.\nNOTE: The One Club reserves the right to review \"late-night, ran-once\" and launch versions. If The One Club, at its sole discretion, determines that the work was created expressly for award show entry, the penalty will hold.\n\nDoes The One Show’s “fake work” policy now cover false statements or manufactured footage in case studies?\nYes. Beginning with the 2026 awards, our longstanding prohibition on fake work has been expanded. In addition to banning work created solely for awards consideration, any intentional misrepresentation in case studies — including falsified outcomes, fabricated or staged executions, misleading narratives, or manipulated footage — is now a direct violation of our integrity standards and may result in disqualification and a 3 year ban.\n\nWhat has The One Show done to strengthen how integrity violations are identified?\nSeveral measures have been reinforced for 2026. All entrants must now certify the authenticity of their submissions at entry, verification letters remain mandatory to confirm both release and accuracy, and our judging platform includes new flagging tools so jurors can raise concerns about questionable work. A dedicated 3–6 week review window before winners are announced allows us to thoroughly investigate any flagged entries to protect the integrity of the awards.\n\n\nPAYMENT\nHow can I pay for my entries?\nWe accept payments by all major credit cards, check or via wire transfer. Credit card payments are subject to a 3% processing fee. Wire transfer payments are subject to a $35 USD processing fee.\nNOTE: All payments must reach The One Club within 15 days of the invoice date.\nFor any payment questions, please contact accounting@oneclub.org.\n\nWho should the check be made out to?\nPlease make sure all checks are made payable to: The One Club for Creativity, Inc.\nNOTE: ALL CHECKS MUST BE IN U.S. DOLLARS DRAWN ON A U.S. BANK.\n\nHow do I add my Tax ID or VAT number to my invoice?\nYour Tax ID or VAT number can be added under the Account Holder section of your account details. Once added to your account, this number will then automatically appear on your invoice(s) after Checkout.\nNOTE: The billing details can be edited for any invoice on the Invoices section of your account.\n\nHow do I add a PO number to my invoice?\nOnce you have the PO number for your invoice, go to the Invoices section of your account and click the pencil icon to the right of the invoice documents. The PO number"
    },
    "联系": {
      "url": "https://oneshow.org/contact/",
      "text": "This website stores cookies on your computer to improve your website experience and provide more personalized services to you.\n\nAcceptDecline\nCONTACT US\n\nPlease view our FAQ page for answers to common questions. If your question is not listed there, please contact the One Show team.\n\nNOTE: Our business hours are Monday – Friday, 10:00am – 6:00pm ET (15:00 – 23:00 GMT).\n\nEMAIL\n\nSend us an email and you will receive a response within two business days. For questions about what category to enter, please include a link to your work so that we can provide you with the best recommendations.\n\noneshow@oneclub.org\n\nPHONE\n\nThe One Show team is available by phone during our business hours.\n\n212-979-1900\next. 501\n\nVIDEO CALL\n\nIf you would like to utilize a screen share or discuss things face-to-face during our business hours, you can schedule a Zoom video call with a member of the One Show team.\n\nPlease email oneshow@oneclub.org to schedule a video call.\n\n\n\n   \n\nTHE ONE CLUB FOR CREATIVITY\n450 W 31ST STREET, 6TH FLOOR\nNEW YORK, NY 10001\n212.979.1900\n\nFOLLOW US\n     \nABOUT\nAbout\nBoard\nPartners\nPress\nContact\n\nAWARDS\nThe One Show\nADC Awards\nTDC Awards\nADCE Awards\nONE Asia\nYoung Ones\n\nMEMBERSHIP\nBecome a Member\nCorporate Members\nIndividual Members\nChapters\n\nPROGRAMS\nEducation\nInclusion & Diversity\nCreative Development\nGender Equality\n\n\n© 2026 The One Club for Creativity. All rights reserved."
    },
    "参赛": {
      "url": "https://oneshow.org/enter",
      "text": "This website stores cookies on your computer to improve your website experience and provide more personalized services to you.\n\nAcceptDecline\nPLEASE SIGN IN\nIf you have a One Club or One Show account, log in using those details.\nIf you do not have an account, click the New User button below.\nEmail \nPassword \nPlease click the box below \nNew User? Register Here Forgot Password?\nSign In\n\n\n   \n\nTHE ONE CLUB FOR CREATIVITY\n450 W 31ST STREET, 6TH FLOOR\nNEW YORK, NY 10001\n212.979.1900\n\nFOLLOW US\n     \nABOUT\nAbout\nBoard\nPartners\nPress\nContact\n\nAWARDS\nThe One Show\nADC Awards\nTDC Awards\nADCE Awards\nONE Asia\nYoung Ones\n\nMEMBERSHIP\nBecome a Member\nCorporate Members\nIndividual Members\nChapters\n\nPROGRAMS\nEducation\nInclusion & Diversity\nCreative Development\nGender Equality\n\n\n© 2026 The One Club for Creativity. All rights reserved."
    }
  },
  "page_count": 10
}