{
  "basic_info": {
    "website": "https://oneshow.org/",
    "name": "Home / The One Show 2026",
    "description": ""
  },
  "raw_content": {
    "homepage": "Home / The One Show 2026 The One Show Toggle Menu Ceremony About The One Show Awards Archive The One Club for Creativity Jury Info Deadlines & Dates Categories Eligibility & Rules Entry Fees Submission Media Specs Payment Awards Rankings Terms & Definitions Help FAQ Contact Us Entry Showcase Choose your language English Chinese Sign In Register No notices at this time Finalists Announced The 2026 One Show Finalists are here! Awards will be publicly released May 14. Celebrate this year's winners with us May 15 in New York City at the ceremony. See the List Entry Deadlines 2025–2026 Super Early Deadline October 31, 2025 Early Deadline December 12, 2025 Regular Deadline January 23, 2026 Extended Deadline February 6, 2026 Final Deadline February 20, 2026 Your Work, Crystallized. The One Show is where the world's best ideas rise to the top. For over 50 years, the Pencil has stood as one of the most respected honors in advertising, design, and beyond. And at the pinnacle: the Crystal Pencil, awarded only to Best of Discipline winners—peer-to-peer recognition from a jury of over 300 global creative leaders. Winning here is hard. That's why it matters. The One Show represents integrity, bold thinking, and the highest level of creative excellence across the industry. With disciplines spanning the full spectrum of creativity—from timeless formats like Print and Film to cutting-edge categories in Gaming, Creative Use of AI, and the brand-new Creator Content discipline—The One Show continues to evolve alongside the work it honors. 2026 also sees the debut of The One Show Indies, a dedicated competition for independent shops proving you don't need scale to make impact. Winners are celebrated on May 15, 2026, during Creative Week in New York City—a week-long global festival from The One Club for Creativity, the world’s foremost nonprofit supporting and celebrating the creative community. This is your moment. Explore the categories. Enter your boldest work. Claim your place among the world’s best. Explore Categories About The One Show 2026 Jury Entry Resources Entry Guide Deadlines &amp; Dates Eligibility &amp; Rules Disciplines &amp; Categories Entry Fees Submission Media Specs One Show FAQ Contact Us Notable for The One Show 2026 Category Highlights Explore the latest categories shaping the future of advertising and design. Creative Use of AI Creator Content Creative Marketer Design &amp; Branding Design in Advertising The One Show Indies Commitment to Integrity Integrity has always been the foundation of The One Show. For over 50 years, we have upheld the principle that true creative excellence must also be authentic, fair, and transparent. In 2026, we renew that commitment with even stronger standards that protect the legacy of the Pencil and the trust of the global creative community. Read more Award Intelligence For the first time, entrants to The One Show can gain meaningful insight into how their work performed in the jury room—through a new AI-powered feedback tool designed to educate, clarify, and elevate future submissions. This optional service transforms the often-mysterious judging process into actionable learning, helping entrants better understand why a piece resonated with judges and how award decisions were made. Learn more One Show Pencils Create Entry GOLD / SILVER / BRONZE PENCILS Icons of achievement that honor ideas distinguished by brilliance, craft, and lasting impact CRYSTAL PENCIL Awarded to Best of Disciplines, Best of Non-Profit, and the year's top ranked winners—including agencies, production studios, networks, and more BEST OF SHOW PENCIL The pinnacle honor—recognizing the single most defining idea of the year Explore the Special Awards View CREATIVE MARKETER Honoring a senior brand leader whose vision and bravery elevate creativity as a core driver of success GREEN PENCIL Celebrating creativity that helps our planet thrive SDG PENCIL Honoring ideas that drive global progress FUSION PENCIL Recognizing creativity rooted in equity and inclusion PENTA PENCIL Awarding enduring excellence in brand-agency partnership THE ONE CLUB FOR CREATIVITY 450 W 31ST STREET, 6TH FLOOR NEW YORK, NY 10001 212.979.1900 FOLLOW US ABOUT About Board Partners Press Contact AWARDS The One Show ADC Awards TDC Awards ADCE Awards ONE Asia Young Ones MEMBERSHIP Become a Member Corporate Members Individual Members Chapters PROGRAMS Education Inclusion &amp; Diversity Creative Development Gender Equality © The One Club for Creativity. All rights reserved. window.embeddedChatbotConfig = { chatbotId: \"G60CjZ7Qzr0pDtsMedjE4\", domain: \"www.chatbase.co\" }"
  },
  "extracted": {
    "fees": {},
    "dates": {
      "deadline": "October 31, 2025"
    },
    "contact": {
      "phone": "212.979.1900"
    },
    "organizer": null,
    "categories": []
  },
  "enrichment_timestamp": "2026-04-20T10:32:30.891Z"
}